[
  {
    "category": "interesting",
    "title": "Canada' is an Indian word meaning 'Big Village'.",
    "_id": "572bcacd0cf046574a3dbea0"
  },
  {
    "category": "interesting",
    "title": "In the average lifetime, a person will walk the equivalent of 5 times around the equator.",
    "_id": "572bcacd0cf046574a3dbe9f"
  },
  {
    "category": "interesting",
    "title": "A barnacle has the largest penis of any other animal in relation to its size.",
    "_id": "572bcacd0cf046574a3dbe9e"
  },
  {
    "category": "interesting",
    "title": "Daniel Boone hated coonskin caps.",
    "_id": "572bcacc0cf046574a3dbe9b"
  },
  {
    "category": "interesting",
    "title": "Residents of Houston, Texas lead the U.S. in eating out - approximately 4.6 times per week.",
    "_id": "572bcacc0cf046574a3dbe9a"
  },
  {
    "category": "interesting",
    "title": "People say 'bless you' when you sneeze because your heart stops for a millisecond.",
    "_id": "572bcacc0cf046574a3dbe98"
  },
  {
    "category": "interesting",
    "title": "The number 'four' is considered unlucky in Japan because it is pronounced the same as 'death'.",
    "_id": "572bcacc0cf046574a3dbe97"
  },
  {
    "category": "interesting",
    "title": "The longest one-syllable word in the English language is 'screeched.' ",
    "_id": "572bcacb0cf046574a3dbe95"
  },
  {
    "category": "interesting",
    "title": "Gorillas often sleep for up to fourteen hours a day.",
    "_id": "572bcacb0cf046574a3dbe94"
  },
  {
    "category": "interesting",
    "title": "Elephants have the longest pregnancy in the animal kingdom at 22 months. The longest human pregnancy on record is 17 months, 11 days.",
    "_id": "572bcacb0cf046574a3dbe92"
  },
  {
    "category": "interesting",
    "title": "Most insects are beneficial to people because they eat other insects, pollinate crops, are food for other animals, make products we use (like honey and silk) or have medical uses.",
    "_id": "572bcaca0cf046574a3dbe8f"
  },
  {
    "category": "interesting",
    "title": "Entomophobia is the fear of insects.",
    "_id": "572bcaca0cf046574a3dbe8e"
  },
  {
    "category": "interesting",
    "title": "Baby robins eat 14 feet of earthworms every day",
    "_id": "572bcaca0cf046574a3dbe8d"
  },
  {
    "category": "interesting",
    "title": "Every day, 7% of the US eats at McDonald’s.",
    "_id": "572bcac90cf046574a3dbe8b"
  },
  {
    "category": "interesting",
    "title": "At latitude 60 degrees south you can sail all the way around the world.",
    "_id": "572bcac90cf046574a3dbe8a"
  },
  {
    "category": "interesting",
    "title": "In Miami, Florida, roosting vultures have taken to snatching poodles from rooftop patios.",
    "_id": "572bcac90cf046574a3dbe89"
  },
  {
    "category": "interesting",
    "title": "Camels have three eyelids to protect themselves from blowing sand.",
    "_id": "572bcac90cf046574a3dbe88"
  },
  {
    "category": "interesting",
    "title": "Every person, including identical twins, has a unique eye & tongue print along with their finger print.",
    "_id": "572bcac80cf046574a3dbe87"
  },
  {
    "category": "interesting",
    "title": "Two-thirds of the world’s eggplant is grown in New Jersey.",
    "_id": "572bcac80cf046574a3dbe86"
  },
  {
    "category": "interesting",
    "title": "Any free moving liquid in outer space will form itself into a sphere because of its surface tension.",
    "_id": "572bcac80cf046574a3dbe85"
  },
  {
    "category": "interesting",
    "title": "Warren Beatty and Shirley McLaine are brother and sister.",
    "_id": "572bcac80cf046574a3dbe84"
  },
  {
    "category": "interesting",
    "title": "Dr. Seuss coined the word nerd in his 1950 book 'If I Ran The Zoo.'",
    "_id": "572bcac70cf046574a3dbe82"
  },
  {
    "category": "interesting",
    "title": "Sex is the safest tranquilizer in the world. IT IS 10 TIMES MORE EFFECTIVE THAN VALIUM.",
    "_id": "572bcac70cf046574a3dbe81"
  },
  {
    "category": "interesting",
    "title": "Rhythm is the longest English word without a vowel.",
    "_id": "572bcac70cf046574a3dbe80"
  },
  {
    "category": "interesting",
    "title": "On average, 100 people choke to death on ballpoint pens every year.",
    "_id": "572bcac70cf046574a3dbe7f"
  },
  {
    "category": "interesting",
    "title": "In Italy, 17 is considered an unlucky number. In Japan, 4 is considered an unlucky number.",
    "_id": "572bcac70cf046574a3dbe7e"
  },
  {
    "category": "interesting",
    "title": "The town of Calma, Chile in the Atacama Desert has never had rain.",
    "_id": "572bcac60cf046574a3dbe7d"
  },
  {
    "category": "interesting",
    "title": "The first streetlights in America were installed in Philadelphia around 1757.",
    "_id": "572bcac60cf046574a3dbe7c"
  },
  {
    "category": "interesting",
    "title": "All of the clocks in the movie 'Pulp Fiction' are stuck on 4:20. ",
    "_id": "572bcac60cf046574a3dbe7b"
  },
  {
    "category": "interesting",
    "title": "The human feet perspire half a pint of fluid a day",
    "_id": "572bcac60cf046574a3dbe7a"
  },
  {
    "category": "interesting",
    "title": "A cockroach can live several weeks with its head cut off!",
    "_id": "572bcac50cf046574a3dbe78"
  },
  {
    "category": "interesting",
    "title": "Rubber bands last longer when refrigerated.",
    "_id": "572bcac50cf046574a3dbe77"
  },
  {
    "category": "interesting",
    "title": "Pennsylvania was the first colony to legalize witchcraft.",
    "_id": "572bcac50cf046574a3dbe76"
  },
  {
    "category": "interesting",
    "title": "Australian Rules football was originally designed to give cricketers something to play during the off season.",
    "_id": "572bcac50cf046574a3dbe75"
  },
  {
    "category": "interesting",
    "title": "The largest taxi fleet in the world is found in Mexico City. The city boasts a fleet of over 60,000 taxis.",
    "_id": "572bcac50cf046574a3dbe74"
  },
  {
    "category": "interesting",
    "title": "The Simpsons is the longest running animated series on TV.",
    "_id": "572bcac40cf046574a3dbe73"
  },
  {
    "category": "interesting",
    "title": "Some worms will eat themselves if they can't find any food!",
    "_id": "572bcac40cf046574a3dbe72"
  },
  {
    "category": "interesting",
    "title": "In 1980, a Las Vegas hospital suspended workers for betting on when patients would die.",
    "_id": "572bcac40cf046574a3dbe71"
  },
  {
    "category": "interesting",
    "title": "There are 10 human body parts that are only 3 letters long (eye hip arm leg ear toe jaw rib lip gum).",
    "_id": "572bcac40cf046574a3dbe70"
  },
  {
    "category": "interesting",
    "title": "If you were to take a taxicab from New York City to Los Angeles, it would cost you $8,325.",
    "_id": "572bcac40cf046574a3dbe6f"
  },
  {
    "category": "interesting",
    "title": "No word in the English language rhymes with month, orange, silver, or purple.",
    "_id": "572bcac30cf046574a3dbe6e"
  },
  {
    "category": "interesting",
    "title": "I am. is the shortest complete sentence in the English language.",
    "_id": "572bcac30cf046574a3dbe6c"
  },
  {
    "category": "interesting",
    "title": "The electric chair was invented by a dentist.",
    "_id": "572bcac30cf046574a3dbe6b"
  },
  {
    "category": "interesting",
    "title": "During the chariot scene in 'Ben Hur,' a small red car can be seen in the distance.",
    "_id": "572bcac30cf046574a3dbe6a"
  },
  {
    "category": "interesting",
    "title": "If you travel across the Russia, you will cross seven time zones.",
    "_id": "572bcac20cf046574a3dbe69"
  },
  {
    "category": "interesting",
    "title": "Pearls melt in vinegar.",
    "_id": "572bcac20cf046574a3dbe66"
  },
  {
    "category": "interesting",
    "title": "$283,200 is the absolute highest amount of money you can win on Jeopardy.",
    "_id": "572bcac20cf046574a3dbe65"
  },
  {
    "category": "interesting",
    "title": "The average raindrop falls at 7 miles per hour.",
    "_id": "572bcac10cf046574a3dbe64"
  },
  {
    "category": "interesting",
    "title": "Happy as a clam is from the expression happy as a clam at high tide. Clams are only harvested when the tide is out.",
    "_id": "572bcac10cf046574a3dbe63"
  },
  {
    "category": "interesting",
    "title": "A cesium atom in an atomic clock beats 9,192,631,770 times a second.",
    "_id": "572bcac10cf046574a3dbe61"
  },
  {
    "category": "interesting",
    "title": "A hydrodaktulpsychicharmonica is a variety of musical glasses.",
    "_id": "572bcac10cf046574a3dbe60"
  },
  {
    "category": "interesting",
    "title": "A penny whistle has six finger holes.",
    "_id": "572bcac00cf046574a3dbe5e"
  },
  {
    "category": "interesting",
    "title": "Sharkskin has tiny tooth-like scales all over.",
    "_id": "572bcac00cf046574a3dbe5c"
  },
  {
    "category": "interesting",
    "title": "George Washington is the only man whose birthday is a legal holiday in every state of the U.S as of a few years ago.",
    "_id": "572bcac00cf046574a3dbe5b"
  },
  {
    "category": "interesting",
    "title": "Some people say that when the black bands on the Woolybear caterpillar are wide, a cold winter is coming.",
    "_id": "572bcabf0cf046574a3dbe5a"
  },
  {
    "category": "interesting",
    "title": "A strand from the web of the golden spider is as strong as a steel wire of the same size.",
    "_id": "572bcabf0cf046574a3dbe57"
  },
  {
    "category": "interesting",
    "title": "The plastic things on the end of shoelaces are called aglets.",
    "_id": "572bcabe0cf046574a3dbe55"
  },
  {
    "category": "interesting",
    "title": "If the Earth was smooth, the ocean would cover the entire surface to a depth of 12,000 feet.",
    "_id": "572bcabe0cf046574a3dbe54"
  },
  {
    "category": "interesting",
    "title": "All the swans in England are property of the Queen.",
    "_id": "572bcabe0cf046574a3dbe53"
  },
  {
    "category": "interesting",
    "title": "Groaking is to watch people eating in hopes that they will offer you some.",
    "_id": "572bcabd0cf046574a3dbe50"
  },
  {
    "category": "interesting",
    "title": "Most household dust is made of dead skin cells.",
    "_id": "572bcabd0cf046574a3dbe4f"
  },
  {
    "category": "interesting",
    "title": "Baby Ruth candy bar was named after Grover Cleveland’s daughter, Ruth, not the baseball player.",
    "_id": "572bcabd0cf046574a3dbe4e"
  },
  {
    "category": "interesting",
    "title": "The sixth sick sheik’s sixth sheep’s sick' is said to be the toughest tongue twister in English.",
    "_id": "572bcabd0cf046574a3dbe4d"
  },
  {
    "category": "interesting",
    "title": "April is Earthquake Preparedness month. For a little added incentive, consider this- The most powerful earthquake to strike the United States occurred in 1811 in New Madrid, Missouri. The quake shook more than one million square miles, and was felt as far as 1,000 miles away.",
    "_id": "572bcabd0cf046574a3dbe4c"
  },
  {
    "category": "interesting",
    "title": "Clans long ago that wanted to get rid of their unwanted people without killing them use to burn down their houses--hence the expression get fired.",
    "_id": "572bcabc0cf046574a3dbe4b"
  },
  {
    "category": "interesting",
    "title": "The most sensitive cluster of nerves is at the base of the spine.",
    "_id": "572bcabc0cf046574a3dbe4a"
  },
  {
    "category": "interesting",
    "title": "A Boeing 747s wingspan is longer than the Wright brother's first flight.",
    "_id": "572bcabc0cf046574a3dbe49"
  },
  {
    "category": "interesting",
    "title": "Anteaters prefer termites to ants.",
    "_id": "572bcabc0cf046574a3dbe48"
  },
  {
    "category": "interesting",
    "title": "French speaking residents of Belgium are called Walloons.",
    "_id": "572bcabc0cf046574a3dbe47"
  },
  {
    "category": "interesting",
    "title": "A shark can detect one part of blood in 100 million parts of water.",
    "_id": "572bcabb0cf046574a3dbe46"
  },
  {
    "category": "interesting",
    "title": "After eating, the housefly regurgitates its food and eats it again.",
    "_id": "572bcabb0cf046574a3dbe45"
  },
  {
    "category": "interesting",
    "title": "The Beetham Tower has 47 floors.",
    "_id": "572bcabb0cf046574a3dbe44"
  },
  {
    "category": "interesting",
    "title": "Dueling is legal in Paraguay as long as both parties are registered blood donors.",
    "_id": "572bcabb0cf046574a3dbe43"
  },
  {
    "category": "interesting",
    "title": "Jamaica has the most churches per square mile than any other country in the world.",
    "_id": "572bcabb0cf046574a3dbe42"
  },
  {
    "category": "interesting",
    "title": "Golden toads are so rare that a biological reserve has been specifically created for them.",
    "_id": "572bcaba0cf046574a3dbe41"
  },
  {
    "category": "interesting",
    "title": "Columbia University is the second largest landowner in New York City, after the Catholic Church.",
    "_id": "572bcaba0cf046574a3dbe3f"
  },
  {
    "category": "interesting",
    "title": "The cheetah is the only cat that can't retract its claws.",
    "_id": "572bcaba0cf046574a3dbe3e"
  },
  {
    "category": "interesting",
    "title": "According to Dr. David Gems, a British geneticist, sex-craved male mice, who spend 5 to 11 hours per day pursuing female mice, could live years longer if they abstained.",
    "_id": "572bcaba0cf046574a3dbe3d"
  },
  {
    "category": "interesting",
    "title": "Every time you lick a stamp, you're consuming 1/10 of a calorie.",
    "_id": "572bcab90cf046574a3dbe3c"
  },
  {
    "category": "interesting",
    "title": "Hawaii is the only coffee producing state.",
    "_id": "572bcab90cf046574a3dbe3b"
  },
  {
    "category": "interesting",
    "title": "The name Jeep comes from 'GP', the army abbreviation for General Purpose.",
    "_id": "572bcab90cf046574a3dbe3a"
  },
  {
    "category": "interesting",
    "title": "A full moon always rises at sunset.",
    "_id": "572bcab90cf046574a3dbe38"
  },
  {
    "category": "interesting",
    "title": "US gold coins used to say 'In Gold We Trust'.",
    "_id": "572bcab80cf046574a3dbe37"
  },
  {
    "category": "interesting",
    "title": "Alligators cannot move backwards.",
    "_id": "572bcab80cf046574a3dbe36"
  },
  {
    "category": "interesting",
    "title": "25% of a human’s bones are in its feet.",
    "_id": "572bcab80cf046574a3dbe35"
  },
  {
    "category": "interesting",
    "title": "A lightning bolt generates temperatures five times hotter than those found on the sun's surface.",
    "_id": "572bcab80cf046574a3dbe34"
  },
  {
    "category": "interesting",
    "title": "Salt Lake City, Utah has a law against carrying an unwrapped ukulele on the street.",
    "_id": "572bcab80cf046574a3dbe33"
  },
  {
    "category": "interesting",
    "title": "Bats always turn left when exiting a cave.",
    "_id": "572bcab70cf046574a3dbe31"
  },
  {
    "category": "interesting",
    "title": "In downtown Lima, Peru, there is a large brass statue dedicated to Winnie-the-Pooh.",
    "_id": "572bcab70cf046574a3dbe2f"
  },
  {
    "category": "interesting",
    "title": "The past-tense of the English word 'dare' is 'durst'",
    "_id": "572bcab60cf046574a3dbe2d"
  },
  {
    "category": "interesting",
    "title": "The first novel ever written on a typewriter is Tom Sawyer.",
    "_id": "572bcab60cf046574a3dbe2c"
  },
  {
    "category": "interesting",
    "title": "A squirrel cannot contract or carry the rabies virus.",
    "_id": "572bcab60cf046574a3dbe2a"
  },
  {
    "category": "interesting",
    "title": "One quarter of the bones in your body, are in your feet!",
    "_id": "572bcab60cf046574a3dbe29"
  },
  {
    "category": "interesting",
    "title": "Stewardesses is the longest word typed with only the left hand.",
    "_id": "572bcab50cf046574a3dbe28"
  },
  {
    "category": "interesting",
    "title": "An iguana can stay under water for twenty-eight minutes.",
    "_id": "572bcab50cf046574a3dbe27"
  },
  {
    "category": "interesting",
    "title": "City with the most Roll Royces per capita: Hong Kong.",
    "_id": "572bcab50cf046574a3dbe26"
  },
  {
    "category": "interesting",
    "title": "For every 'normal' webpage, there are five porn pages.",
    "_id": "572bcab50cf046574a3dbe25"
  },
  {
    "category": "interesting",
    "title": "Cyprus has a map on its flag.",
    "_id": "572bcab50cf046574a3dbe24"
  },
  {
    "category": "interesting",
    "title": "US Dollar bills are made out of cotton and linen.",
    "_id": "572bcab40cf046574a3dbe23"
  }
]
